{
    "defaults": {
        "build_timeout": "20 minutes",
        "test_timeout": "45 minutes"
    },
    "flavors": [
        {
            "usd_flavor": "usd",
            "usd_ver": "25.11",
            "python_ver": "3.12",
            "cxx_abi": "2.35",
            "coverage": true,
            "platforms": ["windows-x86_64", "linux-x86_64", "linux-aarch64"]
        },
        {
            "usd_flavor": "usd",
            "usd_ver": "25.02",
            "python_ver": "3.12",
            "cxx_abi": "2.35",
            "coverage": true,
            "platforms": ["windows-x86_64", "linux-x86_64", "linux-aarch64"]
        },
        {
            "usd_flavor": "usd",
            "usd_ver": "24.05",
            "python_ver": "3.11",
            "cxx_abi": "2.35",
            "coverage": false,
            "platforms": ["windows-x86_64", "linux-x86_64", "linux-aarch64"]
        }
    ]
}